CHANGELOG.txt
LICENSE.txt
MANIFEST.in
NOTES.txt
README.txt
ez_setup.py
setup.cfg
setup.py
admin/process_doc.py
doc/connecting.xhtml
doc/index.xhtml
doc/installing.xhtml
doc/output.xhtml
doc/stylesheet.css
doc/template-sf.tpl
doc/template.tpl
doc/tutorials.xhtml
src/PyPerforce.egg-info/PKG-INFO
src/PyPerforce.egg-info/SOURCES.txt
src/PyPerforce.egg-info/dependency_links.txt
src/PyPerforce.egg-info/requires.txt
src/PyPerforce.egg-info/top_level.txt
src/PyPerforce.egg-info/zip-safe
src/perforce/__init__.py
src/perforce/api.cpp
src/perforce/connection.py
src/perforce/forms.py
src/perforce/objects.py
src/perforce/results.py
src/perforce/async/__init__.py
src/perforce/async/connection.py
src/perforce/async/objects.py
src/perforce/tests/__init__.py
src/perforce/tests/api.py
src/perforce/tests/connection.py
src/perforce/tests/forms.py
src/perforce/tests/objects.py
src/perforce/tests/server.py
test/testAsyncPerforce.py
third-party/p4api/cygwinx86/Jamfile
third-party/p4api/cygwinx86/Jamrules
third-party/p4api/cygwinx86/Version
third-party/p4api/cygwinx86/clientapi.h
third-party/p4api/cygwinx86/clientmerge.h
third-party/p4api/cygwinx86/clientuser.cc
third-party/p4api/cygwinx86/clientuser.h
third-party/p4api/cygwinx86/datetime.h
third-party/p4api/cygwinx86/debug.h
third-party/p4api/cygwinx86/diff.h
third-party/p4api/cygwinx86/echoctl.h
third-party/p4api/cygwinx86/enviro.h
third-party/p4api/cygwinx86/error.h
third-party/p4api/cygwinx86/errorlog.h
third-party/p4api/cygwinx86/errornum.h
third-party/p4api/cygwinx86/filesys.h
third-party/p4api/cygwinx86/handler.h
third-party/p4api/cygwinx86/hostenv.h
third-party/p4api/cygwinx86/i18napi.h
third-party/p4api/cygwinx86/ident.h
third-party/p4api/cygwinx86/keepalive.h
third-party/p4api/cygwinx86/libclient.a
third-party/p4api/cygwinx86/librpc.a
third-party/p4api/cygwinx86/libsupp.a
third-party/p4api/cygwinx86/msgclient.h
third-party/p4api/cygwinx86/netconnect.h
third-party/p4api/cygwinx86/ntservice.h
third-party/p4api/cygwinx86/options.h
third-party/p4api/cygwinx86/p4tags.h
third-party/p4api/cygwinx86/pathsys.h
third-party/p4api/cygwinx86/runcmd.h
third-party/p4api/cygwinx86/samplemain.cc
third-party/p4api/cygwinx86/signaler.h
