Metadata-Version: 1.0
Name: PyPerforce
Version: 0.3a1
Summary: A Python interface for the Perforce SCM
Home-page: http://pyperforce.sourceforge.net/
Author: Lewis Baker
Author-email: lewisbaker@users.sourceforge.net
License: Proprietary License (see LICENSE.txt)
Download-URL: http://sourceforge.net/project/showfiles.php?group_id=162781
Platform: UNKNOWN
Classifier: License :: Other/Proprietary License
Classifier: Intended Audience :: by End-User Class :: Developers
Classifier: Intended Audience :: by End-User Class :: System Administrators
Classifier: Topic :: Software Development :: Version Control
Classifier: Programming Language :: C++
Classifier: Programming Language :: Python
Classifier: Operating System :: Emulation and API Compatibility :: Cygwin (MS Windows)
Classifier: Operating System :: Grouping and Descriptive Categories :: 32-bit MS Windows (NT/2000/XP)
Classifier: Operating System :: Modern (Vendor-Supported) Desktop Operating Systems :: Linux
Classifier: Translations :: English
